tap_norwaycitybikeapi/__init__.py
tap_norwaycitybikeapi/client.py
tap_norwaycitybikeapi/streams.py
tap_norwaycitybikeapi/tap.py
tap_norwaycitybikeapi-0.1.1.dist-info/METADATA
tap_norwaycitybikeapi-0.1.1.dist-info/WHEEL
tap_norwaycitybikeapi-0.1.1.dist-info/entry_points.txt
tap_norwaycitybikeapi-0.1.1.dist-info/RECORD
