Metadata-Version: 2.1
Name: tap-norwaycitybikeapi
Version: 0.1.1
Summary: `tap-norwaycitybikeapi` is a Singer tap for NorwayCityBikeAPI, built with the Meltano Singer SDK.
License: Apache 2.0
Keywords: ELT,NorwayCityBikeAPI
Author: Kristian André Jakobsen
Author-email: k.andrejakobsen@gmail.com
Requires-Python: >=3.8,<3.12
Classifier: License :: Other/Proprietary License
Classifier: Programming Language :: Python :: 3
Classifier: Programming Language :: Python :: 3.8
Classifier: Programming Language :: Python :: 3.9
Classifier: Programming Language :: Python :: 3.10
Classifier: Programming Language :: Python :: 3.11
Provides-Extra: s3
Requires-Dist: fs-s3fs (>=1.1.1,<2.0.0) ; extra == "s3"
Requires-Dist: pre-commit (>=3.2.2,<4.0.0)
Requires-Dist: requests (>=2.28.2,<3.0.0)
Requires-Dist: singer-sdk (>=0.24.0,<0.25.0)
